reflected_light_sim/__init__.py
reflected_light_sim/reflectance.py
reflected_light_sim-0.1.1.dist-info/LICENSE
reflected_light_sim-0.1.1.dist-info/METADATA
reflected_light_sim-0.1.1.dist-info/WHEEL
reflected_light_sim-0.1.1.dist-info/top_level.txt
reflected_light_sim-0.1.1.dist-info/RECORD
